fjson/__init__.py
fjson/main.py
fjson-0.1.5.dist-info/LICENSE
fjson-0.1.5.dist-info/METADATA
fjson-0.1.5.dist-info/WHEEL
fjson-0.1.5.dist-info/top_level.txt
fjson-0.1.5.dist-info/RECORD
