Metadata-Version: 2.1
Name: fjson
Version: 0.1.5
Summary: Python JSON writer with float formatting
Home-page: https://github.com/nschloe/fjson
Author: Nico Schlömer
Author-email: nico.schloemer@gmail.com
License: MIT
Project-URL: Code, https://github.com/nschloe/fjson
Project-URL: Issues, https://github.com/nschloe/fjson/issues
Project-URL: Funding, https://github.com/sponsors/nschloe
Platform: UNKNOWN
Classifier: Development Status :: 4 - Beta
Classifier: Intended Audience :: Science/Research
Classifier: License :: OSI Approved :: MIT License
Classifier: Operating System :: OS Independent
Classifier: Programming Language :: Python
Classifier: Programming Language :: Python :: 3
Classifier: Programming Language :: Python :: 3.7
Classifier: Programming Language :: Python :: 3.8
Classifier: Programming Language :: Python :: 3.9
Classifier: Programming Language :: Python :: 3.10
Classifier: Topic :: Utilities
Requires-Python: >=3.7
License-File: LICENSE
